odoo/addons/ssi_policy_mixin/README.rst
odoo/addons/ssi_policy_mixin/__init__.py
odoo/addons/ssi_policy_mixin/__manifest__.py
odoo/addons/ssi_policy_mixin/menu.xml
odoo/addons/ssi_policy_mixin/i18n/ssi_policy_mixin.pot
odoo/addons/ssi_policy_mixin/models/__init__.py
odoo/addons/ssi_policy_mixin/models/mixin_policy.py
odoo/addons/ssi_policy_mixin/models/policy_template.py
odoo/addons/ssi_policy_mixin/models/policy_template_detail.py
odoo/addons/ssi_policy_mixin/security/ir.model.access.csv
odoo/addons/ssi_policy_mixin/static/description/icon.png
odoo/addons/ssi_policy_mixin/views/policy_template_detail_views.xml
odoo/addons/ssi_policy_mixin/views/policy_template_views.xml
odoo14_addon_ssi_policy_mixin-14.0.1.3.2.dist-info/METADATA
odoo14_addon_ssi_policy_mixin-14.0.1.3.2.dist-info/WHEEL
odoo14_addon_ssi_policy_mixin-14.0.1.3.2.dist-info/top_level.txt
odoo14_addon_ssi_policy_mixin-14.0.1.3.2.dist-info/RECORD
